climweb_wdqms/__init__.py
climweb_wdqms/admin.py
climweb_wdqms/apps.py
climweb_wdqms/models.py
climweb_wdqms/serializers.py
climweb_wdqms/tests.py
climweb_wdqms/urls.py
climweb_wdqms/views.py
climweb_wdqms/management/__init__.py
climweb_wdqms/management/commands/__init__.py
climweb_wdqms/management/commands/wdqms_stats.py
climweb_wdqms/migrations/0001_initial.py
climweb_wdqms/migrations/__init__.py
climweb_wdqms-0.0.9.dist-info/METADATA
climweb_wdqms-0.0.9.dist-info/WHEEL
climweb_wdqms-0.0.9.dist-info/top_level.txt
climweb_wdqms-0.0.9.dist-info/RECORD
